focal_frequency_loss/__init__.py
focal_frequency_loss/focal_frequency_loss.py
focal_frequency_loss-0.3.0.dist-info/LICENSE.md
focal_frequency_loss-0.3.0.dist-info/METADATA
focal_frequency_loss-0.3.0.dist-info/WHEEL
focal_frequency_loss-0.3.0.dist-info/top_level.txt
focal_frequency_loss-0.3.0.dist-info/RECORD
