Metadata-Version: 2.1
Name: focal-frequency-loss
Version: 0.3.0
Summary: Focal Frequency Loss for Image Reconstruction and Synthesis - Official PyTorch Implementation
Home-page: https://github.com/EndlessSora/focal-frequency-loss
Author: Liming Jiang
Author-email: liming002@ntu.edu.sg
License: UNKNOWN
Platform: UNKNOWN
Classifier: Programming Language :: Python :: 3
Classifier: License :: OSI Approved :: MIT License
Classifier: Operating System :: OS Independent
Requires-Python: >=3.5
License-File: LICENSE.md
Requires-Dist: torch (>=1.1.0)
Requires-Dist: numpy
